memory.v
module memory(clk,read,d_out,address);
input      clk,read;
input      [3:0] address; 
output reg [3:0] d_out;

reg [3:0] data_ROM [15:0];

initial $readmemb("data_ROM.mem",data_ROM);

always @(posedge clk) begin
	if (read) begin
		d_out <= data_ROM[address]; 
	end
end

endmodule

mem_tb.v
module mem_tb;
	reg clk,read;
	reg  [3:0] address; 
	wire [3:0] d_out;
	integer i; 
	initial begin 
		$dumpfile("v.vcd");
		$dumpvars();
	end
	
	memory m1 (clk,read,d_out,address);

	initial begin
		clk = 1'b1;
		read = 1'b1;
		address = 1'b0;
		for ( i = 0; i < 15; i = i + 1) begin
			@(posedge clk);
			address <= address + 1;
		end
		read = 1'b0;
		#5000;
		$finish;
	end
	always #10 clk = ~clk;
endmodule

v.vcd
$date
	Fri Jan 29 17:59:02 2021
$end
$version
	Icarus Verilog
$end
$timescale
	1s
$end
$scope module mem_tb $end
$var wire 4 ! d_out [3:0] $end
$var reg 4 " address [3:0] $end
$var reg 1 # clk $end
$var reg 1 $ read $end
$var integer 32 % i [31:0] $end
$scope module m1 $end
$var wire 4 & address [3:0] $end
$var wire 1 # clk $end
$var wire 1 $ read $end
$var reg 4 ' d_out [3:0] $end
$upscope $end
$upscope $end
$enddefinitions $end
#0
$dumpvars
b1000 '
b0 &
b0 %
1$
1#
b0 "
b1000 !
$end
#10
0#
#20
b1 "
b1 &
b1 %
1#
#30
0#
#40
b10 "
b10 &
b10 %
1#
#50
0#
#60
b11 "
b11 &
b0 !
b0 '
b11 %
1#
#70
0#
#80
b1 !
b1 '
b100 "
b100 &
b100 %
1#
#90
0#
#100
b101 "
b101 &
b10 !
b10 '
b101 %
1#
#110
0#
#120
b11 !
b11 '
b110 "
b110 &
b110 %
1#
#130
0#
#140
b111 "
b111 &
b101 !
b101 '
b111 %
1#
#150
0#
#160
b110 !
b110 '
b1000 "
b1000 &
b1000 %
1#
#170
0#
#180
b1001 "
b1001 &
b0 !
b0 '
b1001 %
1#
#190
0#
#200
b1 !
b1 '
b1010 "
b1010 &
b1010 %
1#
#210
0#
#220
b1011 "
b1011 &
b1011 %
1#
#230
0#
#240
b1100 "
b1100 &
b1100 %
1#
#250
0#
#260
b1101 "
b1101 &
b1000 !
b1000 '
b1101 %
1#
#270
0#
#280
b1001 !
b1001 '
b1110 "
b1110 &
b1110 %
1#
#290
0#
#300
b1111 "
b1111 &
b1110 !
b1110 '
0$
b1111 %
1#
